{
  "platform": "EBAY_AU",
  "listing_id": "ebay_au:278093444445",
  "url": "https://www.ebay.com.au/itm/278093444445",
  "title": "Acer Predator Helios Neo 18 \" 250hz U9 16gb Ddr5 1tb SSD RTX 5070 8gb W11 Pro _",
  "price_aud": 3551.0,
  "seller_name": "simpletek-italia",
  "seller_rating": null,
  "condition_code": null,
  "condition_label": null,
  "shipping_type": null,
  "pickup_location_text": null,
  "category_path": "Computers/Tablets & Networking > Laptops & Netbooks",
  "full_listing_text": "Acer Predator Helios Neo 18 \" 250hz U9 16gb Ddr5 1tb SSD RTX 5070 8gb W11 Pro _",
  "scraped_at": "2026-07-04T08:12:18.579429Z",
  "gpu_name": "RTX 5070",
  "vram_capacity": 16,
  "cpu_name": "U9",
  "total_system_ram": 16,
  "storage": "1tb SSD",
  "egpu_model": null,
  "touchscreen_digitizer": null,
  "exact_model_name": "Predator Helios Neo 18"
}