{
  "platform": "EBAY_AU",
  "listing_id": "ebay_au:147384310689",
  "url": "https://www.ebay.com.au/itm/147384310689",
  "title": "Lenovo ThinkPad P15 Gen 1 15.6\" 4K OLED Touch Xeon W-10885M 64GB RAM 2TB SSD RTX",
  "price_aud": 2140.04,
  "seller_name": "veteranpcpartners",
  "seller_rating": null,
  "condition_code": null,
  "condition_label": "Used",
  "shipping_type": null,
  "pickup_location_text": null,
  "category_path": "Computers/Tablets & Networking > Laptops & Netbooks",
  "full_listing_text": "Lenovo ThinkPad P15 Gen 1 15.6\" 4K OLED Touch Xeon W-10885M 64GB RAM 2TB SSD RTX",
  "scraped_at": "2026-07-04T08:12:18.504439Z",
  "gpu_name": "RTX",
  "vram_capacity": null,
  "cpu_name": "Xeon W-10885M",
  "total_system_ram": 64,
  "storage": "2TB SSD",
  "egpu_model": null,
  "touchscreen_digitizer": true,
  "exact_model_name": "ThinkPad P15 Gen 1"
}